HISTORY.txt
README.txt
TODO
bootstrap.py
buildout.cfg
setup.py
./gocept/__init__.py
./gocept/devtools/__init__.py
./gocept/devtools/copyright.py
./gocept/devtools/tests.py
gocept/__init__.py
gocept.devtools.egg-info/PKG-INFO
gocept.devtools.egg-info/SOURCES.txt
gocept.devtools.egg-info/dependency_links.txt
gocept.devtools.egg-info/entry_points.txt
gocept.devtools.egg-info/namespace_packages.txt
gocept.devtools.egg-info/not-zip-safe
gocept.devtools.egg-info/requires.txt
gocept.devtools.egg-info/top_level.txt
gocept/devtools/__init__.py
gocept/devtools/copyright.py
gocept/devtools/copyright.txt
gocept/devtools/tests.py