Metadata-Version: 1.0
Name: gocept.devtools
Version: 0.3
Summary: Small utilities for managing code.
Home-page: UNKNOWN
Author: Christian Theune
Author-email: ct@gocept.com
License: ZPL 2.1
Platform: UNKNOWN
